MANIFEST.in
Readme.rst
setup.cfg
setup.py
clubsandwich/__init__.py
clubsandwich/babysit.py
clubsandwich/datastore.py
clubsandwich/director.py
clubsandwich/draw.py
clubsandwich/event_dispatcher.py
clubsandwich/generators.py
clubsandwich/geom.py
clubsandwich/line_of_sight.py
clubsandwich/pcg32.py
clubsandwich/tilemap.py
clubsandwich/xp_loader.py
clubsandwich.egg-info/PKG-INFO
clubsandwich.egg-info/SOURCES.txt
clubsandwich.egg-info/dependency_links.txt
clubsandwich.egg-info/entry_points.txt
clubsandwich.egg-info/requires.txt
clubsandwich.egg-info/top_level.txt
clubsandwich/blt/__init__.py
clubsandwich/blt/context.py
clubsandwich/blt/loop.py
clubsandwich/blt/nice_terminal.py
clubsandwich/blt/rexpaint_image.py
clubsandwich/blt/state.py
clubsandwich/ui/__init__.py
clubsandwich/ui/collection_list.py
clubsandwich/ui/firstrespondercontainerview.py
clubsandwich/ui/layout_options.py
clubsandwich/ui/misc_views.py
clubsandwich/ui/text_input.py
clubsandwich/ui/ui_scene.py
clubsandwich/ui/view.py
tests/__init__.py
tests/test_datastore.py