Metadata-Version: 1.1
Name: clubsandwich
Version: 0.1.3
Summary: A roguelike framework
Home-page: http://steveasleep.com/clubsandwich
Author: Steve Johnson
Author-email: steve@steveasleep.com
License: MIT
Keywords: bearlibterminal,roguelike
Platform: UNKNOWN
Classifier: Development Status :: 3 - Alpha
Classifier: Intended Audience :: Developers
Classifier: License :: OSI Approved :: MIT License
Classifier: Programming Language :: Python :: 3
Classifier: Programming Language :: Python :: 3.4
Classifier: Programming Language :: Python :: 3.5
Classifier: Programming Language :: Python :: 3.6
